ua2.patch-2.0.0-py2.7-nspkg.pth
ua2/patch/__init__.py
ua2/patch/models.py
ua2/patch/backends/__init__.py
ua2/patch/backends/base.py
ua2/patch/backends/json.py
ua2/patch/backends/py.py
ua2/patch/backends/sh.py
ua2/patch/backends/sql.py
ua2/patch/management/__init__.py
ua2/patch/management/commands/__init__.py
ua2/patch/management/commands/patch.py
ua2/patch/migrations/0001_initial.py
ua2/patch/migrations/__init__.py
ua2.patch-2.0.0.dist-info/DESCRIPTION.rst
ua2.patch-2.0.0.dist-info/METADATA
ua2.patch-2.0.0.dist-info/RECORD
ua2.patch-2.0.0.dist-info/WHEEL
ua2.patch-2.0.0.dist-info/eager_resources.txt
ua2.patch-2.0.0.dist-info/entry_points.txt
ua2.patch-2.0.0.dist-info/metadata.json
ua2.patch-2.0.0.dist-info/namespace_packages.txt
ua2.patch-2.0.0.dist-info/top_level.txt
