Metadata-Version: 2.0
Name: ua2.patch
Version: 2.0.0
Summary: UA2WEB Django patch system
Home-page: https://bitbucket.org/ua2web/ua2.patch
Author: UA2WEB
Author-email: alex@ua2web.com
License: MIT
Keywords: django migration utility
Platform: UNKNOWN
Classifier: Development Status :: 4 - Beta
Classifier: Intended Audience :: Developers
Classifier: License :: OSI Approved :: MIT License
Classifier: Programming Language :: Python :: 2
Classifier: Programming Language :: Python :: 3
Provides-Extra: dev
Provides-Extra: test
